pyhetznerserver/__init__.py
pyhetznerserver/client.py
pyhetznerserver/example_usage.py
pyhetznerserver/exceptions.py
pyhetznerserver/managers/__init__.py
pyhetznerserver/managers/server_manager.py
pyhetznerserver/models/__init__.py
pyhetznerserver/models/base.py
pyhetznerserver/models/nested.py
pyhetznerserver/models/server.py
pyhetznerserver-1.2.4.dist-info/licenses/AUTHORS.md
pyhetznerserver-1.2.4.dist-info/licenses/LICENSE
pyhetznerserver-1.2.4.dist-info/METADATA
pyhetznerserver-1.2.4.dist-info/WHEEL
pyhetznerserver-1.2.4.dist-info/top_level.txt
pyhetznerserver-1.2.4.dist-info/RECORD
