Metadata-Version: 2.4
Name: pyhetznerserver
Version: 1.2.4
Summary: A modern, type-safe Python library for Hetzner Cloud Server management
Home-page: https://github.com/DeepPythonist/PyHetznerServer
Author: Mohammad Rasol Esfandiari
Author-email: Mohammad Rasol Esfandiari <mrasolesfandiari@gmail.com>
Maintainer-email: Mohammad Rasol Esfandiari <mrasolesfandiari@gmail.com>
License: MIT
Project-URL: Homepage, https://github.com/DeepPythonist/PyHetznerServer
Project-URL: Documentation, https://pyhetznerserver.readthedocs.io/
Project-URL: Repository, https://github.com/DeepPythonist/PyHetznerServer
Project-URL: Issues, https://github.com/DeepPythonist/PyHetznerServer/issues
Project-URL: Changelog, https://github.com/DeepPythonist/PyHetznerServer/blob/main/CHANGELOG.md
Keywords: hetzner,cloud,server,api,management,infrastructure,hosting,vps
Classifier: Development Status :: 4 - Beta
Classifier: Intended Audience :: Developers
Classifier: Intended Audience :: System Administrators
Classifier: License :: OSI Approved :: MIT License
Classifier: Operating System :: OS Independent
Classifier: Programming Language :: Python :: 3
Classifier: Programming Language :: Python :: 3.8
Classifier: Programming Language :: Python :: 3.9
Classifier: Programming Language :: Python :: 3.10
Classifier: Programming Language :: Python :: 3.11
Classifier: Programming Language :: Python :: 3.12
Classifier: Topic :: Internet :: WWW/HTTP
Classifier: Topic :: Software Development :: Libraries :: Python Modules
Classifier: Topic :: System :: Systems Administration
Classifier: Topic :: Utilities
Classifier: Typing :: Typed
Requires-Python: >=3.8
License-File: LICENSE
License-File: AUTHORS.md
Requires-Dist: requests>=2.28.0
Provides-Extra: dev
Requires-Dist: pytest>=7.0.0; extra == "dev"
Requires-Dist: pytest-cov>=4.0.0; extra == "dev"
Requires-Dist: black>=22.0.0; extra == "dev"
Requires-Dist: isort>=5.10.0; extra == "dev"
Requires-Dist: flake8>=5.0.0; extra == "dev"
Requires-Dist: mypy>=1.0.0; extra == "dev"
Requires-Dist: pre-commit>=2.20.0; extra == "dev"
Provides-Extra: docs
Requires-Dist: sphinx>=5.0.0; extra == "docs"
Requires-Dist: sphinx-rtd-theme>=1.2.0; extra == "docs"
Requires-Dist: sphinx-autodoc-typehints>=1.19.0; extra == "docs"
Provides-Extra: test
Requires-Dist: pytest>=7.0.0; extra == "test"
Requires-Dist: pytest-cov>=4.0.0; extra == "test"
Requires-Dist: pytest-mock>=3.10.0; extra == "test"
Requires-Dist: responses>=0.22.0; extra == "test"
Dynamic: author
Dynamic: home-page
Dynamic: license-file
Dynamic: requires-python
